[
    {
        "key": "datr",
        "value": "iOFOaFp2BCgKajYZSNTYNSfK",
        "domain": "facebook.com",
        "path": "/",
        "hostOnly": false,
        "creation": "2025-09-15T01:55:25.542Z",
        "lastAccessed": "2025-09-15T01:55:25.542Z"
    },
    {
        "key": "sb",
        "value": "iOFOaKUf4KXgU8Y0zKjd0m-3",
        "domain": "facebook.com",
        "path": "/",
        "hostOnly": false,
        "creation": "2025-09-15T01:55:25.542Z",
        "lastAccessed": "2025-09-15T01:55:25.542Z"
    },
    {
        "key": "vpd",
        "value": "v1%3B651x360x3",
        "domain": "facebook.com",
        "path": "/",
        "hostOnly": false,
        "creation": "2025-09-15T01:55:25.542Z",
        "lastAccessed": "2025-09-15T01:55:25.542Z"
    },
    {
        "key": "ps_l",
        "value": "1",
        "domain": "facebook.com",
        "path": "/",
        "hostOnly": false,
        "creation": "2025-09-15T01:55:25.542Z",
        "lastAccessed": "2025-09-15T01:55:25.542Z"
    },
    {
        "key": "ps_n",
        "value": "1",
        "domain": "facebook.com",
        "path": "/",
        "hostOnly": false,
        "creation": "2025-09-15T01:55:25.542Z",
        "lastAccessed": "2025-09-15T01:55:25.542Z"
    },
    {
        "key": "pas",
        "value": "61558336351586%3ApFtezBkYXK%2C61577269175937%3AWru5QEEBKH%2C61551082137728%3AYsumGnbZnE",
        "domain": "facebook.com",
        "path": "/",
        "hostOnly": false,
        "creation": "2025-09-15T01:55:25.542Z",
        "lastAccessed": "2025-09-15T01:55:25.542Z"
    },
    {
        "key": "m_pixel_ratio",
        "value": "3",
        "domain": "facebook.com",
        "path": "/",
        "hostOnly": false,
        "creation": "2025-09-15T01:55:25.542Z",
        "lastAccessed": "2025-09-15T01:55:25.542Z"
    },
    {
        "key": "wd",
        "value": "360x803",
        "domain": "facebook.com",
        "path": "/",
        "hostOnly": false,
        "creation": "2025-09-15T01:55:25.542Z",
        "lastAccessed": "2025-09-15T01:55:25.542Z"
    },
    {
        "key": "c_user",
        "value": "61558336351586",
        "domain": "facebook.com",
        "path": "/",
        "hostOnly": false,
        "creation": "2025-09-15T01:55:25.542Z",
        "lastAccessed": "2025-09-15T01:55:25.542Z"
    },
    {
        "key": "xs",
        "value": "22%3AEwnCHeMQ4wN0JA%3A2%3A1757901205%3A-1%3A-1",
        "domain": "facebook.com",
        "path": "/",
        "hostOnly": false,
        "creation": "2025-09-15T01:55:25.543Z",
        "lastAccessed": "2025-09-15T01:55:25.543Z"
    },
    {
        "key": "fr",
        "value": "01uTp9Yui5bFpOpuq.AWexw3-78ua8pNWwB92_llYPm8pxBCdsYQrw7s8RXq3ftMcyMZ0.BoTuGI..AAA.0.0.Box3GX.AWe2R6kvgmaUz3BcDcjTleT-J5A",
        "domain": "facebook.com",
        "path": "/",
        "hostOnly": false,
        "creation": "2025-09-15T01:55:25.543Z",
        "lastAccessed": "2025-09-15T01:55:25.543Z"
    },
    {
        "key": "locale",
        "value": "hi_IN",
        "domain": "facebook.com",
        "path": "/",
        "hostOnly": false,
        "creation": "2025-09-15T01:55:25.543Z",
        "lastAccessed": "2025-09-15T01:55:25.543Z"
    },
    {
        "key": "fbl_st",
        "value": "101033721%3BT%3A29298353",
        "domain": "facebook.com",
        "path": "/",
        "hostOnly": false,
        "creation": "2025-09-15T01:55:25.543Z",
        "lastAccessed": "2025-09-15T01:55:25.543Z"
    },
    {
        "key": "wl_cbv",
        "value": "v2%3Bclient_version%3A2904%3Btimestamp%3A1757901207",
        "domain": "facebook.com",
        "path": "/",
        "hostOnly": false,
        "creation": "2025-09-15T01:55:25.543Z",
        "lastAccessed": "2025-09-15T01:55:25.543Z"
    }
]
